icrypt/__init__.py
icrypt/__version__.py
icrypt/decorators.py
icrypt/icrypt.py
icrypt/icrypt_old.py
icrypt/pgp_handler.py
icrypt-0.1.1.dist-info/LICENSE
icrypt-0.1.1.dist-info/METADATA
icrypt-0.1.1.dist-info/WHEEL
icrypt-0.1.1.dist-info/top_level.txt
icrypt-0.1.1.dist-info/RECORD
