Metadata-Version: 2.1
Name: icrypt
Version: 0.1.1
Summary: A simple pgp encryption and decryption module for Python 3.6+
Home-page: https://github.com/rhcproc/icrypt
Author: Hans Park
Author-email: rhcproc@gmail.com
License: MIT
Classifier: Programming Language :: Python :: 3.6
Classifier: Programming Language :: Python :: 3.7
Classifier: Programming Language :: Python :: 3.8
Classifier: Programming Language :: Python :: 3.9
Classifier: Programming Language :: Python :: 3.10
Classifier: License :: OSI Approved :: MIT License
Classifier: Operating System :: OS Independent
Requires-Python: >=3.5
License-File: LICENSE
Requires-Dist: pgpy (>=0.5.2)
